yaml_for_humans/__init__.py
yaml_for_humans/__init__.pyi
yaml_for_humans/cli.py
yaml_for_humans/cli.pyi
yaml_for_humans/document_processors.py
yaml_for_humans/document_processors.pyi
yaml_for_humans/dumper.py
yaml_for_humans/dumper.pyi
yaml_for_humans/emitter.py
yaml_for_humans/emitter.pyi
yaml_for_humans/formatting_aware.py
yaml_for_humans/formatting_aware.pyi
yaml_for_humans/formatting_emitter.py
yaml_for_humans/formatting_emitter.pyi
yaml_for_humans/multi_document.py
yaml_for_humans/multi_document.pyi
yaml_for_humans/py.typed
yaml_for_humans-1.4.4.dist-info/WHEEL
yaml_for_humans-1.4.4.dist-info/entry_points.txt
yaml_for_humans-1.4.4.dist-info/METADATA
yaml_for_humans-1.4.4.dist-info/RECORD
