Metadata-Version: 2.3
Name: yaml-for-humans
Version: 1.4.4
Summary: Human-friendly YAML formatting with intelligent sequence handling and priority key ordering
Keywords: yaml,formatting,kubernetes,devops,configuration
Author: Stephen D. Spencer
Author-email: Stephen D. Spencer <stephen@revsys.com>
Classifier: Development Status :: 5 - Production/Stable
Classifier: Intended Audience :: Developers
Classifier: Intended Audience :: System Administrators
Classifier: License :: OSI Approved :: BSD License
Classifier: Operating System :: OS Independent
Classifier: Programming Language :: Python :: 3
Classifier: Programming Language :: Python :: 3.8
Classifier: Programming Language :: Python :: 3.9
Classifier: Programming Language :: Python :: 3.10
Classifier: Programming Language :: Python :: 3.11
Classifier: Programming Language :: Python :: 3.12
Classifier: Topic :: Software Development :: Libraries :: Python Modules
Classifier: Topic :: System :: Systems Administration
Classifier: Topic :: Text Processing :: Markup
Requires-Dist: pyyaml>=6.0
Requires-Dist: click>=8.0.0 ; extra == 'cli'
Requires-Python: >=3.8
Project-URL: Repository, https://github.com/gladiatr72/yaml-for-humans
Provides-Extra: cli
